elide/__init__.py
elide/__main__.py
elide/app.py
elide/boardscatter.py
elide/boardview.py
elide/calendar.kv
elide/calendar.py
elide/card.kv
elide/card.py
elide/charmenu.kv
elide/charmenu.py
elide/charsview.kv
elide/charsview.py
elide/collide.py
elide/dummy.kv
elide/dummy.py
elide/elide.kv
elide/game.py
elide/gen.kv
elide/gen.py
elide/imagestackproxy.py
elide/logview.kv
elide/logview.py
elide/menu.kv
elide/menu.py
elide/pallet.kv
elide/pallet.py
elide/pawn.py
elide/pawnspot.py
elide/rulebooks.kv
elide/rulebooks.py
elide/rulesview.kv
elide/rulesview.py
elide/screen.kv
elide/screen.py
elide/spritebuilder.kv
elide/spritebuilder.py
elide/statcfg.kv
elide/statcfg.py
elide/statlist.py
elide/stepper.kv
elide/stepper.py
elide/stores.kv
elide/stores.py
elide/timestream.kv
elide/timestream.py
elide/util.py
elide/assets/Symbola.ttf
elide/assets/next.png
elide/assets/parchmentBasic.png
elide/assets/polygons-0.png
elide/assets/polygons.atlas
elide/assets/right.png
elide/assets/kenney1bit/colored-transparent_packed.png
elide/assets/kenney1bit/kenney1bit.atlas
elide/assets/rltiles/amulet-0.png
elide/assets/rltiles/amulet.atlas
elide/assets/rltiles/arm-0.png
elide/assets/rltiles/arm.atlas
elide/assets/rltiles/armor-0.png
elide/assets/rltiles/armor.atlas
elide/assets/rltiles/base-0.png
elide/assets/rltiles/base.atlas
elide/assets/rltiles/beard-0.png
elide/assets/rltiles/beard.atlas
elide/assets/rltiles/body-0.png
elide/assets/rltiles/body.atlas
elide/assets/rltiles/book-0.png
elide/assets/rltiles/book.atlas
elide/assets/rltiles/boot-0.png
elide/assets/rltiles/boot.atlas
elide/assets/rltiles/cloak-0.png
elide/assets/rltiles/cloak.atlas
elide/assets/rltiles/dc-mon-0.png
elide/assets/rltiles/dc-mon.atlas
elide/assets/rltiles/dungeon-0.png
elide/assets/rltiles/dungeon.atlas
elide/assets/rltiles/floor-0.png
elide/assets/rltiles/floor.atlas
elide/assets/rltiles/food-0.png
elide/assets/rltiles/food.atlas
elide/assets/rltiles/gem-0.png
elide/assets/rltiles/gem.atlas
elide-0.23.1.dist-info/licenses/LICENSE
elide-0.23.1.dist-info/METADATA
elide-0.23.1.dist-info/WHEEL
elide-0.23.1.dist-info/top_level.txt
elide-0.23.1.dist-info/RECORD
