Metadata-Version: 2.4
Name: elide
Version: 0.23.1
Summary: Extensible Life Simulator Engine Development Environment
Author-email: Zachary Spector <public@zacharyspector.com>
License-Expression: AGPL-3.0-only
Project-URL: Homepage, https://codeberg.org/clayote/Lisien
Project-URL: Bug Tracker, https://codeberg.org/clayote/Lisien/issues
Classifier: Programming Language :: Python :: 3
Classifier: Operating System :: OS Independent
Classifier: Development Status :: 3 - Alpha
Classifier: Intended Audience :: Developers
Requires-Python: ~=3.12
License-File: LICENSE
Requires-Dist: lisien==0.23.1
Requires-Dist: kivy>=2.0.0
Requires-Dist: kivy-deps.glew; sys_platform == "win32"
Requires-Dist: kivy-deps.sdl2; sys_platform == "win32"
Requires-Dist: pygments>=2.7.4
Dynamic: license-file
